dictionary/__init__.py
dictionary/dictionary.py
bilkent_2021_2022_spring_cs453_hw1_ziya_mukhtarov-2.0.1.dist-info/METADATA
bilkent_2021_2022_spring_cs453_hw1_ziya_mukhtarov-2.0.1.dist-info/WHEEL
bilkent_2021_2022_spring_cs453_hw1_ziya_mukhtarov-2.0.1.dist-info/top_level.txt
bilkent_2021_2022_spring_cs453_hw1_ziya_mukhtarov-2.0.1.dist-info/RECORD
