Metadata-Version: 2.1
Name: bilkent-2021-2022-spring-cs453-hw1-ziya-mukhtarov
Version: 2.0.1
Summary: UNKNOWN
Author: Ziya Mukhtarov
License: UNKNOWN
Platform: UNKNOWN
Requires-Python: >=3.8
Requires-Dist: requests (>=2.23.0)
